{"SubjectNumber":"1234","FallingSpeed":2.0,"NumberSpawnDelayTime":1.5,"TaskStartAt":"2022-08-26 17:19:20Z","taskEvents":[{"ID":1,"EventAt":"2022-08-26 17:19:20Z","eventTypeString":"NumberCreate","DestroyPosition":0.0},{"ID":2,"EventAt":"2022-08-26 17:19:22Z","eventTypeString":"TimePause","DestroyPosition":0.0},{"ID":3,"EventAt":"2022-08-26 17:19:23Z","eventTypeString":"NumberCreate","DestroyPosition":0.0},{"ID":4,"EventAt":"2022-08-26 17:19:24Z","eventTypeString":"TypeCorrect","DestroyPosition":0.0},{"ID":5,"EventAt":"2022-08-26 17:19:24Z","eventTypeString":"TypeCorrect","DestroyPosition":0.0},{"ID":6,"EventAt":"2022-08-26 17:19:25Z","eventTypeString":"TypeCorrect","DestroyPosition":0.0},{"ID":7,"EventAt":"2022-08-26 17:19:25Z","eventTypeString":"NumberDestroy","DestroyPosition":5.930502414703369},{"ID":8,"EventAt":"2022-08-26 17:19:25Z","eventTypeString":"NumberCreate","DestroyPosition":0.0},{"ID":9,"EventAt":"2022-08-26 17:19:27Z","eventTypeString":"NumberCreate","DestroyPosition":0.0},{"ID":10,"EventAt":"2022-08-26 17:19:27Z","eventTypeString":"TypeCorrect","DestroyPosition":0.0},{"ID":11,"EventAt":"2022-08-26 17:19:27Z","eventTypeString":"TypeCorrect","DestroyPosition":0.0},{"ID":12,"EventAt":"2022-08-26 17:19:27Z","eventTypeString":"TypeCorrect","DestroyPosition":0.0},{"ID":13,"EventAt":"2022-08-26 17:19:27Z","eventTypeString":"NumberDestroy","DestroyPosition":6.89808988571167},{"ID":14,"EventAt":"2022-08-26 17:19:28Z","eventTypeString":"NumberCreate","DestroyPosition":0.0},{"ID":15,"EventAt":"2022-08-26 17:19:28Z","eventTypeString":"TypeCorrect","DestroyPosition":0.0},{"ID":16,"EventAt":"2022-08-26 17:19:29Z","eventTypeString":"TypeCorrect","DestroyPosition":0.0},{"ID":17,"EventAt":"2022-08-26 17:19:29Z","eventTypeString":"TypeCorrect","DestroyPosition":0.0},{"ID":18,"EventAt":"2022-08-26 17:19:29Z","eventTypeString":"NumberDestroy","DestroyPosition":8.146307945251465},{"ID":19,"EventAt":"2022-08-26 17:19:30Z","eventTypeString":"NumberCreate","DestroyPosition":0.0},{"ID":20,"EventAt":"2022-08-26 17:19:31Z","eventTypeString":"TypeCorrect","DestroyPosition":0.0},{"ID":21,"EventAt":"2022-08-26 17:19:31Z","eventTypeString":"TypeCorrect","DestroyPosition":0.0},{"ID":22,"EventAt":"2022-08-26 17:19:31Z","eventTypeString":"NumberCreate","DestroyPosition":0.0},{"ID":23,"EventAt":"2022-08-26 17:19:32Z","eventTypeString":"TypeCorrect","DestroyPosition":0.0},{"ID":24,"EventAt":"2022-08-26 17:19:32Z","eventTypeString":"NumberDestroy","DestroyPosition":10.082863807678223},{"ID":25,"EventAt":"2022-08-26 17:19:33Z","eventTypeString":"NumberCreate","DestroyPosition":0.0},{"ID":26,"EventAt":"2022-08-26 17:19:34Z","eventTypeString":"NumberCreate","DestroyPosition":0.0},{"ID":27,"EventAt":"2022-08-26 17:19:34Z","eventTypeString":"TimePause","DestroyPosition":0.0},{"ID":28,"EventAt":"2022-08-26 17:19:35Z","eventTypeString":"TimePause","DestroyPosition":0.0}]}
